ipyvue/ForceLoad.py
ipyvue/Html.py
ipyvue/Template.py
ipyvue/VueComponentRegistry.py
ipyvue/VueTemplateWidget.py
ipyvue/VueWidget.py
ipyvue/__init__.py
ipyvue/_version.py
ipyvue/labextension/package.json
ipyvue/labextension/static/125.465cc3afc1a74ee7901d.js
ipyvue/labextension/static/140.81618e2257248b1f4c55.js
ipyvue/labextension/static/144.f2941768ec558bb0d380.js
ipyvue/labextension/static/144.f2941768ec558bb0d380.js.LICENSE.txt
ipyvue/labextension/static/261.89c5ab601c941e359a5d.js
ipyvue/labextension/static/486.653c734a29168093bd34.js
ipyvue/labextension/static/486.653c734a29168093bd34.js.LICENSE.txt
ipyvue/labextension/static/848.259f5eb22e93a150effc.js
ipyvue/labextension/static/remoteEntry.334a7f83049b6661d899.js
ipyvue/labextension/static/style.js
ipyvue/labextension/static/third-party-licenses.json
ipyvue/nbextension/extension.js
ipyvue/nbextension/index.js
ipyvue/nbextension/index.js.LICENSE.txt
ipyvue/nbextension/index.js.map
ipyvue/nbextension/nodeps.js
ipyvue/nbextension/nodeps.js.LICENSE.txt
ipyvue/nbextension/nodeps.js.map
ipyvue-1.11.3.data/data/etc/jupyter/nbconfig/notebook.d/jupyter-vue.json
ipyvue-1.11.3.data/data/share/jupyter/lab/extensions/jupyter-vue-1.11.3.tgz
ipyvue-1.11.3.data/data/share/jupyter/labextensions/jupyter-vue/package.json
ipyvue-1.11.3.data/data/share/jupyter/labextensions/jupyter-vue/static/125.465cc3afc1a74ee7901d.js
ipyvue-1.11.3.data/data/share/jupyter/labextensions/jupyter-vue/static/140.81618e2257248b1f4c55.js
ipyvue-1.11.3.data/data/share/jupyter/labextensions/jupyter-vue/static/144.f2941768ec558bb0d380.js
ipyvue-1.11.3.data/data/share/jupyter/labextensions/jupyter-vue/static/144.f2941768ec558bb0d380.js.LICENSE.txt
ipyvue-1.11.3.data/data/share/jupyter/labextensions/jupyter-vue/static/261.89c5ab601c941e359a5d.js
ipyvue-1.11.3.data/data/share/jupyter/labextensions/jupyter-vue/static/486.653c734a29168093bd34.js
ipyvue-1.11.3.data/data/share/jupyter/labextensions/jupyter-vue/static/486.653c734a29168093bd34.js.LICENSE.txt
ipyvue-1.11.3.dist-info/LICENSE
ipyvue-1.11.3.dist-info/METADATA
ipyvue-1.11.3.dist-info/WHEEL
ipyvue-1.11.3.dist-info/top_level.txt
ipyvue-1.11.3.dist-info/RECORD
